{"cameraMode":{"drawMode":0,"name":"Shaded","section":"Shading Mode"},"sceneLighting":true,"audioPlay":false,"sceneViewState":{"m_AlwaysRefresh":false,"showFog":true,"showSkybox":true,"showFlares":true,"showImageEffects":true,"showParticleSystems":true,"showVisualEffectGraphs":true,"m_FxEnabled":true},"in2DMode":false,"pivot":{"x":0.000025272369384765625,"y":1.0440869331359864,"z":1.912064790725708},"rotation":{"x":0.0,"y":0.7071068286895752,"z":0.0,"w":0.7071068286895752},"size":1.2800946235656739,"orthographic":false}